{
  "apiVersion": "1.0",
  "alertMetadata": {
    "district": "Colombo",
    "gaugeStationName": "Nagalagam Street",
    "stationId": "01-10 M",
    "river": "Kelani River",
    "waterLevelThresholds": {
      "warningLevel": 1.2192148,
      "dangerLevel": 1.5240185,
      "extremeDangerLevel": 2.133626
    }
  },
  "issueTimestampSeconds": "1681183086",
  "expirationTimestampSeconds": "1681355886",
  "hasFlooding": false,
  "currentState": {
    "startTimestampSeconds": "1681177073",
    "endTimestampSeconds": "1681177073",
    "severity": "NO_FLOODING"
  },
  "forecastedStates": [
    {
      "startTimestampSeconds": "1681196400",
      "endTimestampSeconds": "1681196400",
      "waterLevelValueMeters": 0.45301095,
      "severity": "NO_FLOODING",
      "waterLevelChange": {
        "lowerBoundMeters": 0.0,
        "upperBoundMeters": 0.0,
        "lowerBoundInches": 0.0,
        "upperBoundInches": 0.0
      }
    }
  ]
}