{
  "apiVersion": "1.0",
  "alertMetadata": {
    "gaugeStationName": "Dalia",
    "stationId": "SW291.5R",
    "river": "Teesta",
    "waterLevelThresholds": {
      "warningLevel": 51.65,
      "dangerLevel": 52.15,
      "extremeDangerLevel": 53.15
    }
  },
  "issueTimestampSeconds": "1681198754",
  "expirationTimestampSeconds": "1681371554",
  "hasFlooding": false,
  "currentState": {
    "startTimestampSeconds": "1681182000",
    "endTimestampSeconds": "1681182000",
    "severity": "NO_FLOODING"
  }
}